{
  "train": true,
  "EXP_NAME": "lcgn_ref",
  "GPUS": "1",
  "SNAPSHOT_FILE": "./exp_clevr/pytorch_ckpt/%s/%04d.ckpt",
  "VOCAB_QUESTION_FILE": "./exp_clevr/data/vocabulary_clevr_locplus.txt",
  "VOCAB_ANSWER_FILE": "./exp_clevr/data/answers_clevr.txt",
  "IMDB_FILE": "./exp_clevr/data/imdb/imdb_%s.npy",
  "IMAGE_DIR": "./exp_clevr/clevr_dataset/images",
  "SPATIAL_FEATURE_DIR": "./exp_clevr/data/features/spatial",
  "FEAT_TYPE": "spatial",
  "INIT_WRD_EMB_FROM_FILE": false,
  "WRD_EMB_INIT_FILE": "",
  "H_FEAT": 14,
  "W_FEAT": 14,
  "D_FEAT": 1152,
  "T_ENCODER": 72,
  "ADD_POS_ENC": true,
  "PE_DIM": 128,
  "PE_SCALE": 1.0,
  "MSG_ITER_NUM": 4,
  "STEM_NORMALIZE": false,
  "STEM_LINEAR": false,
  "STEM_CNN": true,
  "STEM_CNN_DIM": 512,
  "STEM_RENORMALIZE": true,
  "WRD_EMB_DIM": 300,
  "WRD_EMB_FIXED": false,
  "ENC_DIM": 512,
  "CMD_DIM": 512,
  "CMD_INPUT_ACT": "TANH",
  "CTX_DIM": 512,
  "OUT_QUESTION_MUL": true,
  "OUT_CLASSIFIER_DIM": 512,
  "USE_EMA": true,
  "EMA_DECAY_RATE": 0.999,
  "encInputDropout": 0.85,
  "stemDropout": 0.82,
  "qDropout": 0.92,
  "memoryDropout": 0.85,
  "readDropout": 0.85,
  "outputDropout": 0.85,
  "MASK_PADUNK_IN_LOGITS": true,
  "BUILD_VQA": false,
  "BUILD_REF": true,
  "BBOX_IOU_THRESH": 0.5,
  "MATCH_THRESH": 0.75,
  "IMG_H": 320,
  "IMG_W": 480,
  "TRAIN": {
    "SPLIT_VQA": "train",
    "SPLIT_REF": "locplus_train",
    "BATCH_SIZE": 64,
    "START_EPOCH": 0,
    "LOSS_TYPE": "softmax",
    "CLIP_GRADIENTS": true,
    "GRAD_MAX_NORM": 8.0,
    "SOLVER": {
      "LR": 0.0001,
      "LR_DECAY": 0.5
    },
    "MAX_EPOCH": 40,
    "RUN_EVAL": true,
    "EVAL_MAX_NUM": 10000
  },
  "TEST": {
    "SPLIT_VQA": "val",
    "SPLIT_REF": "locplus_val",
    "BATCH_SIZE": 128,
    "EPOCH": 40,
    "DUMP_PRED": false,
    "RESULT_DIR": "./exp_clevr/results/%s/%04d",
    "NUM_VIS": 0,
    "VIS_DIR_PREFIX": "vis",
    "VIS_FILTER_EDGE": true,
    "VIS_EDGE_SCALE": 1.0,
    "VIS_FINAL_REL_TH": 0.025,
    "VIS_FINAL_ABS_TH": 0.025,
    "VIS_MSG_TH": 0.1
  }
}